opentera/OpenTeraServerVersion.py
opentera/__init__.py
opentera/config/ConfigManager.py
opentera/config/__init__.py
opentera/crypto/__init__.py
opentera/crypto/crypto_utils.py
opentera/db/Base.py
opentera/db/SoftDeleteMixin.py
opentera/db/SoftDeleteQueryRewriter.py
opentera/db/SoftInsertMixin.py
opentera/db/__init__.py
opentera/db/models/TeraAsset.py
opentera/db/models/TeraDevice.py
opentera/db/models/TeraDeviceParticipant.py
opentera/db/models/TeraDeviceProject.py
opentera/db/models/TeraDeviceSite.py
opentera/db/models/TeraDeviceSubType.py
opentera/db/models/TeraDeviceType.py
opentera/db/models/TeraParticipant.py
opentera/db/models/TeraParticipantGroup.py
opentera/db/models/TeraProject.py
opentera/db/models/TeraServerSettings.py
opentera/db/models/TeraService.py
opentera/db/models/TeraServiceAccess.py
opentera/db/models/TeraServiceConfig.py
opentera/db/models/TeraServiceConfigSpecific.py
opentera/db/models/TeraServiceProject.py
opentera/db/models/TeraServiceRole.py
opentera/db/models/TeraServiceSite.py
opentera/db/models/TeraSession.py
opentera/db/models/TeraSessionDevices.py
opentera/db/models/TeraSessionEvent.py
opentera/db/models/TeraSessionParticipants.py
opentera/db/models/TeraSessionServices.py
opentera/db/models/TeraSessionType.py
opentera/db/models/TeraSessionTypeProject.py
opentera/db/models/TeraSessionTypeServices.py
opentera/db/models/TeraSessionTypeSite.py
opentera/db/models/TeraSessionUsers.py
opentera/db/models/TeraSite.py
opentera/db/models/TeraTest.py
opentera/db/models/TeraTestInvitation.py
opentera/db/models/TeraTestType.py
opentera/db/models/TeraTestTypeProject.py
opentera/db/models/TeraTestTypeSite.py
opentera/db/models/TeraUser.py
opentera/db/models/TeraUserGroup.py
opentera/db/models/TeraUserPreference.py
opentera/db/models/TeraUserUserGroup.py
opentera/db/models/__init__.py
opentera/events/__init__.py
opentera/forms/TeraDeviceForm.py
opentera/forms/TeraDeviceSubTypeForm.py
opentera/forms/TeraDeviceTypeForm.py
opentera/forms/TeraForm.py
opentera-1.3.0.dist-info/LICENSE
opentera-1.3.0.dist-info/METADATA
opentera-1.3.0.dist-info/WHEEL
opentera-1.3.0.dist-info/top_level.txt
opentera-1.3.0.dist-info/RECORD
